{
  "id": "06",
  "slug": "kit-srm-completo",
  "scheduled_for": "2026-06-20",
  "pillar": "kit",
  "format": "carousel",
  "caption": "Sua escola tem Sala de Recursos Multifuncionais (SRM)? Tem todos os itens obrigatórios pela Resolução do FNDE?\n\nEsse carrossel mostra o que TEM que ter no kit — e onde a maioria das escolas erra.\n\nVai implantar ou ativar SRM em 2026? Chama no direct.\n\n#SRM #InclusaoEscolar #AEE #PDDE #FNDE #EducacaoEspecial",
  "slides_count": 8,
  "status": "pending_review"
}